odoo9_addon_l10n_be_iso20022_pain-9.0.1.0.0.99.dev7-py2.7-nspkg.pth
odoo9_addon_l10n_be_iso20022_pain-9.0.1.0.0.99.dev7.dist-info/METADATA
odoo9_addon_l10n_be_iso20022_pain-9.0.1.0.0.99.dev7.dist-info/RECORD
odoo9_addon_l10n_be_iso20022_pain-9.0.1.0.0.99.dev7.dist-info/WHEEL
odoo9_addon_l10n_be_iso20022_pain-9.0.1.0.0.99.dev7.dist-info/namespace_packages.txt
odoo9_addon_l10n_be_iso20022_pain-9.0.1.0.0.99.dev7.dist-info/top_level.txt
odoo_addons/l10n_be_iso20022_pain/README.rst
odoo_addons/l10n_be_iso20022_pain/__init__.py
odoo_addons/l10n_be_iso20022_pain/__openerp__.py
odoo_addons/l10n_be_iso20022_pain/i18n/fr.po
odoo_addons/l10n_be_iso20022_pain/i18n/l10n_be_iso20022_pain.pot
odoo_addons/l10n_be_iso20022_pain/models/__init__.py
odoo_addons/l10n_be_iso20022_pain/models/account_move_line.py
odoo_addons/l10n_be_iso20022_pain/models/account_payment_line.py
odoo_addons/l10n_be_iso20022_pain/static/description/icon.png
odoo_addons/l10n_be_iso20022_pain/tests/__init__.py
odoo_addons/l10n_be_iso20022_pain/tests/test_l10n_be_iso20022_pain.py
