Metadata-Version: 2.1
Name: odoo9-addon-l10n-be-iso20022-pain
Version: 9.0.1.0.0.99.dev7
Summary: This module adds Belgium-specific support to account_payment_order.
Home-page: https://github.com/OCA/l10n-belgium
Author: ACSONE SA/NV,Odoo Community Association (OCA)
Author-email: support@odoo-community.org
License: AGPL-3
Platform: UNKNOWN
Classifier: Programming Language :: Python
Classifier: Framework :: Odoo
Classifier: License :: OSI Approved :: GNU Affero General Public License v3
Requires-Python: ~=2.7
Requires-Dist: odoo9-addon-account-payment-order
Requires-Dist: odoo (<9.1a,>=9.0a)
